tests/__init__.py
tests/assistant/__init__.py
tests/assistant/datasource/__init__.py
tests/assistant/datasource/test_code_datasource.py
tests/assistant/datasource/test_confluence_datasource.py
tests/assistant/datasource/test_file_indexing.py
tests/assistant/datasource/test_google_datasource.py
tests/assistant/datasource/test_jira_datasource.py
tests/assistant/default_integrations/__init__.py
tests/assistant/default_integrations/test_default_integrations_for_tool.py
tests/assistant/default_integrations/test_default_integrations_for_tool_kit.py
tests/assistant/default_integrations/test_default_integrations_for_tool_with_datasource.py
tests/assistant/test_assistants.py
tests/assistant/tools/__init__.py
tests/assistant/tools/ado/__init__.py
tests/assistant/tools/ado/test_assistant_for_ado_test_plan_tools.py
tests/assistant/tools/ado/test_assistant_for_ado_wiki_tools.py
tests/assistant/tools/ado/test_assistant_for_ado_work_item_tools.py
tests/assistant/tools/cloud/__init__.py
tests/assistant/tools/cloud/test_cloud_tools.py
tests/assistant/tools/codebase/__init__.py
tests/assistant/tools/codebase/test_codebase_tools.py
tests/assistant/tools/datamanagement/__init__.py
tests/assistant/tools/datamanagement/test_assistant_with_data_management_tools.py
tests/assistant/tools/filemanagement/__init__.py
tests/assistant/tools/filemanagement/test_assistant_with_file_management_tools.py
tests/assistant/tools/git/__init__.py
tests/assistant/tools/git/test_assistant_with_git_tools.py
tests/assistant/tools/mcp/__init__.py
tests/assistant/tools/mcp/test_cli_mcp_server.py
tests/assistant/tools/mcp/test_mcp_servers.py
tests/assistant/tools/notification/__init__.py
tests/assistant/tools/notification/test_assistant_notification_tools.py
tests/assistant/tools/openapi/__init__.py
tests/assistant/tools/openapi/test_assistant_with_open_api_tools.py
tests/assistant/tools/plugin/__init__.py
tests/assistant/tools/plugin/test_assistant_with_development_plugin.py
codemie_autotests-0.1.13.dist-info/METADATA
codemie_autotests-0.1.13.dist-info/WHEEL
codemie_autotests-0.1.13.dist-info/RECORD
