Metadata-Version: 2.3
Name: codemie-autotests
Version: 0.1.13
Summary: Autotest for CodeMie backend and UI
Author: Anton Yeromin
Author-email: anton_yeromin@epam.com
Requires-Python: >=3.12,<4.0
Classifier: Programming Language :: Python :: 3
Classifier: Programming Language :: Python :: 3.12
Classifier: Programming Language :: Python :: 3.13
Requires-Dist: PyHamcrest (>=2.1.0,<3.0.0)
Requires-Dist: aws-assume-role-lib (>=2.10.0,<3.0.0)
Requires-Dist: boto3 (>=1.39.8,<2.0.0)
Requires-Dist: codemie-plugins (>=0.1.123,<0.2.0)
Requires-Dist: codemie-sdk-python (>=0.1.109,<0.2.0)
Requires-Dist: pytest (>=8.4.1,<9.0.0)
Requires-Dist: pytest-playwright (>=0.7.0,<0.8.0)
Requires-Dist: pytest-reportportal (>=5.5.2,<6.0.0)
Requires-Dist: pytest-rerunfailures (>=15.1,<16.0)
Requires-Dist: pytest-xdist (>=3.6.1,<4.0.0)
Requires-Dist: python-dotenv (>=1.1.0,<2.0.0)
Requires-Dist: python-gitlab (>=5.6.0,<6.0.0)
Requires-Dist: pyyaml (>=6.0.2,<7.0.0)
Requires-Dist: tzlocal (>=5.3.1,<6.0.0)
